{
    "expiration": "2026-07-02",
    "calls": [
        {
            "contractSymbol": "AAL260702C00005000",
            "lastTradeDate": "2026-06-12 19:11:20+00:00",
            "strike": 5.0,
            "lastPrice": 9.96,
            "bid": 8.8,
            "ask": 12.0,
            "change": 1.5100002,
            "percentChange": 17.869825,
            "volume": 4,
            "openInterest": 706,
            "impliedVolatility": 4.0234424707031256,
            "inTheMoney": true,
            "contractSize": "REGULAR",
            "currency": "USD"
        },
        {
            "contractSymbol": "AAL260702C00006000",
            "lastTradeDate": "2026-06-10 13:32:56+00:00",
            "strike": 6.0,
            "lastPrice": 7.75,
            "bid": 7.75,
            "ask": 9.45,
            "change": 0.0,
            "percentChange": 0.0,
            "volume": 2,
            "openInterest": 338,
            "impliedVolatility": 3.5468761328125,
            "inTheMoney": true,
            "contractSize": "REGULAR",
            "currency": "USD"
        },
        {
            "contractSymbol": "AAL260702C00007000",
            "lastTradeDate": "2026-06-12 16:11:21+00:00",
            "strike": 7.0,
            "lastPrice": 7.87,
            "bid": 6.75,
            "ask": 8.45,
            "change": 1.3699999,
            "percentChange": 21.076921,
            "volume": 6,
            "openInterest": 252,
            "impliedVolatility": 3.0351586621093753,
            "inTheMoney": true,
            "contractSize": "REGULAR",
            "currency": "USD"
        },
        {
            "contractSymbol": "AAL260702C00007500",
            "lastTradeDate": "2026-06-12 19:12:20+00:00",
            "strike": 7.5,
            "lastPrice": 7.47,
            "bid": 6.35,
            "ask": 9.55,
            "change": 1.27,
            "percentChange": 20.483871,
            "volume": 2,
            "openInterest": 52,
            "impliedVolatility": 2.8085967285156253,
            "inTheMoney": true,
            "contractSize": "REGULAR",
            "currency": "USD"
        },
        {
            "contractSymbol": "AAL260702C00008000",
            "lastTradeDate": "2026-06-12 16:15:35+00:00",
            "strike": 8.0,
            "lastPrice": 6.98,
            "bid": 5.75,
            "ask": 7.35,
            "change": 1.29,
            "percentChange": 22.671352,
            "volume": 4,
            "openInterest": 62,
            "impliedVolatility": 2.4062539843749997,
            "inTheMoney": true,
            "contractSize": "REGULAR",
            "currency": "USD"
        },
        {
            "contractSymbol": "AAL260702C00008500",
            "lastTradeDate": "2026-06-11 13:55:39+00:00",
            "strike": 8.5,
            "lastPrice": 5.25,
            "bid": 5.25,
            "ask": 7.75,
            "change": 0.0,
            "percentChange": 0.0,
            "volume": 14,
            "openInterest": 24,
            "impliedVolatility": 1.1875040625,
            "inTheMoney": true,
            "contractSize": "REGULAR",
            "currency": "USD"
        },
        {
            "contractSymbol": "AAL260702C00009000",
            "lastTradeDate": "2026-06-11 16:32:12+00:00",
            "strike": 9.0,
            "lastPrice": 4.7,
            "bid": 4.75,
            "ask": 7.25,
            "change": 0.0,
            "percentChange": 0.0,
            "volume": 4,
            "openInterest": 9,
            "impliedVolatility": 1.0781296093750001,
            "inTheMoney": true,
            "contractSize": "REGULAR",
            "currency": "USD"
        },
        {
            "contractSymbol": "AAL260702C00009500",
            "lastTradeDate": "2026-06-12 19:14:30+00:00",
            "strike": 9.5,
            "lastPrice": 5.48,
            "bid": 4.8,
            "ask": 7.5,
            "change": 1.53,
            "percentChange": 38.734177,
            "volume": 4,
            "openInterest": 3,
            "impliedVolatility": 2.3242229394531244,
            "inTheMoney": true,
            "contractSize": "REGULAR",
            "currency": "USD"
        },
        {
            "contractSymbol": "AAL260702C00010000",
            "lastTradeDate": "2026-06-10 19:39:34+00:00",
            "strike": 10.0,
            "lastPrice": 3.45,
            "bid": 4.55,
            "ask": 5.5,
            "change": 0.0,
            "percentChange": 0.0,
            "volume": 12,
            "openInterest": 2,
            "impliedVolatility": 1.0078174609375,
            "inTheMoney": true,
            "contractSize": "REGULAR",
            "currency": "USD"
        },
        {
            "contractSymbol": "AAL260702C00011000",
            "lastTradeDate": "2026-06-09 15:15:36+00:00",
            "strike": 11.0,
            "lastPrice": 3.15,
            "bid": 3.55,
            "ask": 4.35,
            "change": 0.0,
            "percentChange": 0.0,
            "volume": 4,
            "openInterest": 69,
            "impliedVolatility": 1.4121123144531251,
            "inTheMoney": true,
            "contractSize": "REGULAR",
            "currency": "USD"
        },
        {
            "contractSymbol": "AAL260702C00012000",
            "lastTradeDate": "2026-06-11 19:31:53+00:00",
            "strike": 12.0,
            "lastPrice": 2.27,
            "bid": 2.78,
            "ask": 4.45,
            "change": 0.0,
            "percentChange": 0.0,
            "volume": 3,
            "openInterest": 29,
            "impliedVolatility": 1.421877890625,
            "inTheMoney": true,
            "contractSize": "REGULAR",
            "currency": "USD"
        },
        {
            "contractSymbol": "AAL260702C00012500",
            "lastTradeDate": "2026-06-12 13:30:01+00:00",
            "strike": 12.5,
            "lastPrice": 2.25,
            "bid": 2.31,
            "ask": 3.05,
            "change": 0.80999994,
            "percentChange": 56.249992,
            "volume": 1,
            "openInterest": 78,
            "impliedVolatility": 0.7851583984375,
            "inTheMoney": true,
            "contractSize": "REGULAR",
            "currency": "USD"
        },
        {
            "contractSymbol": "AAL260702C00013000",
            "lastTradeDate": "2026-06-11 17:32:51+00:00",
            "strike": 13.0,
            "lastPrice": 1.25,
            "bid": 1.66,
            "ask": 2.26,
            "change": 0.0,
            "percentChange": 0.0,
            "volume": 15,
            "openInterest": 139,
            "impliedVolatility": 0.7578149218750001,
            "inTheMoney": true,
            "contractSize": "REGULAR",
            "currency": "USD"
        },
        {
            "contractSymbol": "AAL260702C00013500",
            "lastTradeDate": "2026-06-12 19:59:04+00:00",
            "strike": 13.5,
            "lastPrice": 1.7,
            "bid": 1.64,
            "ask": 1.86,
            "change": 0.26,
            "percentChange": 18.055553,
            "volume": 39,
            "openInterest": 275,
            "impliedVolatility": 0.6191444335937502,
            "inTheMoney": true,
            "contractSize": "REGULAR",
            "currency": "USD"
        },
        {
            "contractSymbol": "AAL260702C00014000",
            "lastTradeDate": "2026-06-12 19:52:30+00:00",
            "strike": 14.0,
            "lastPrice": 1.23,
            "bid": 1.2,
            "ask": 1.37,
            "change": 0.13,
            "percentChange": 11.818181,
            "volume": 210,
            "openInterest": 506,
            "impliedVolatility": 0.5214891601562499,
            "inTheMoney": true,
            "contractSize": "REGULAR",
            "currency": "USD"
        },
        {
            "contractSymbol": "AAL260702C00014500",
            "lastTradeDate": "2026-06-12 19:36:44+00:00",
            "strike": 14.5,
            "lastPrice": 0.97,
            "bid": 0.88,
            "ask": 1.03,
            "change": 0.21000004,
            "percentChange": 27.631584,
            "volume": 127,
            "openInterest": 2051,
            "impliedVolatility": 0.5136767382812499,
            "inTheMoney": true,
            "contractSize": "REGULAR",
            "currency": "USD"
        },
        {
            "contractSymbol": "AAL260702C00015000",
            "lastTradeDate": "2026-06-12 19:41:40+00:00",
            "strike": 15.0,
            "lastPrice": 0.69,
            "bid": 0.6,
            "ask": 0.69,
            "change": 0.13,
            "percentChange": 23.214285,
            "volume": 190,
            "openInterest": 1248,
            "impliedVolatility": 0.5136767382812499,
            "inTheMoney": false,
            "contractSize": "REGULAR",
            "currency": "USD"
        },
        {
            "contractSymbol": "AAL260702C00015500",
            "lastTradeDate": "2026-06-12 19:34:51+00:00",
            "strike": 15.5,
            "lastPrice": 0.46,
            "bid": 0.44,
            "ask": 0.52,
            "change": 0.14000002,
            "percentChange": 43.750008,
            "volume": 137,
            "openInterest": 245,
            "impliedVolatility": 0.5117236328125,
            "inTheMoney": false,
            "contractSize": "REGULAR",
            "currency": "USD"
        },
        {
            "contractSymbol": "AAL260702C00016000",
            "lastTradeDate": "2026-06-12 19:56:47+00:00",
            "strike": 16.0,
            "lastPrice": 0.3,
            "bid": 0.28,
            "ask": 0.32,
            "change": 0.050000012,
            "percentChange": 20.000004,
            "volume": 783,
            "openInterest": 1167,
            "impliedVolatility": 0.5097705273437501,
            "inTheMoney": false,
            "contractSize": "REGULAR",
            "currency": "USD"
        },
        {
            "contractSymbol": "AAL260702C00016500",
            "lastTradeDate": "2026-06-12 17:01:12+00:00",
            "strike": 16.5,
            "lastPrice": 0.2,
            "bid": 0.18,
            "ask": 0.2,
            "change": 0.060000002,
            "percentChange": 42.857143,
            "volume": 121,
            "openInterest": 192,
            "impliedVolatility": 0.5019581054687501,
            "inTheMoney": false,
            "contractSize": "REGULAR",
            "currency": "USD"
        },
        {
            "contractSymbol": "AAL260702C00017000",
            "lastTradeDate": "2026-06-12 18:29:51+00:00",
            "strike": 17.0,
            "lastPrice": 0.1,
            "bid": 0.1,
            "ask": 0.16,
            "change": 0.0,
            "percentChange": 0.0,
            "volume": 3,
            "openInterest": 160,
            "impliedVolatility": 0.5097705273437501,
            "inTheMoney": false,
            "contractSize": "REGULAR",
            "currency": "USD"
        },
        {
            "contractSymbol": "AAL260702C00017500",
            "lastTradeDate": "2026-06-11 19:30:19+00:00",
            "strike": 17.5,
            "lastPrice": 0.05,
            "bid": 0.0,
            "ask": 0.3,
            "change": 0.0,
            "percentChange": 0.0,
            "volume": 1,
            "openInterest": 26,
            "impliedVolatility": 0.6113320117187502,
            "inTheMoney": false,
            "contractSize": "REGULAR",
            "currency": "USD"
        },
        {
            "contractSymbol": "AAL260702C00018000",
            "lastTradeDate": "2026-06-11 13:39:59+00:00",
            "strike": 18.0,
            "lastPrice": 0.18,
            "bid": 0.0,
            "ask": 2.17,
            "change": 0.0,
            "percentChange": 0.0,
            "volume": 1,
            "openInterest": 9,
            "impliedVolatility": 1.5341820166015623,
            "inTheMoney": false,
            "contractSize": "REGULAR",
            "currency": "USD"
        },
        {
            "contractSymbol": "AAL260702C00019000",
            "lastTradeDate": "2026-06-09 14:03:37+00:00",
            "strike": 19.0,
            "lastPrice": 0.03,
            "bid": 0.02,
            "ask": 0.1,
            "change": 0.0,
            "percentChange": 0.0,
            "volume": 1,
            "openInterest": 226,
            "impliedVolatility": 0.6562534375000001,
            "inTheMoney": false,
            "contractSize": "REGULAR",
            "currency": "USD"
        },
        {
            "contractSymbol": "AAL260702C00020000",
            "lastTradeDate": "2026-06-10 17:29:48+00:00",
            "strike": 20.0,
            "lastPrice": 0.02,
            "bid": 0.0,
            "ask": 0.25,
            "change": 0.0,
            "percentChange": 0.0,
            "volume": 3,
            "openInterest": 26,
            "impliedVolatility": 0.8945323046874999,
            "inTheMoney": false,
            "contractSize": "REGULAR",
            "currency": "USD"
        },
        {
            "contractSymbol": "AAL260702C00021000",
            "lastTradeDate": "2026-06-08 14:14:52+00:00",
            "strike": 21.0,
            "lastPrice": 0.03,
            "bid": 0.0,
            "ask": 1.02,
            "change": 0.0,
            "percentChange": 0.0,
            "volume": 1,
            "openInterest": 1,
            "impliedVolatility": 1.4960962695312499,
            "inTheMoney": false,
            "contractSize": "REGULAR",
            "currency": "USD"
        }
    ],
    "puts": [
        {
            "contractSymbol": "AAL260702P00005000",
            "lastTradeDate": "2026-06-01 19:27:52+00:00",
            "strike": 5.0,
            "lastPrice": 0.01,
            "bid": 0.0,
            "ask": 0.02,
            "change": 0.0,
            "percentChange": 0.0,
            "volume": NaN,
            "openInterest": 5,
            "impliedVolatility": 1.96875015625,
            "inTheMoney": false,
            "contractSize": "REGULAR",
            "currency": "USD"
        },
        {
            "contractSymbol": "AAL260702P00009500",
            "lastTradeDate": "2026-06-03 16:59:08+00:00",
            "strike": 9.5,
            "lastPrice": 0.02,
            "bid": 0.0,
            "ask": 0.11,
            "change": 0.0,
            "percentChange": 0.0,
            "volume": NaN,
            "openInterest": 1,
            "impliedVolatility": 1.1640666796875,
            "inTheMoney": false,
            "contractSize": "REGULAR",
            "currency": "USD"
        },
        {
            "contractSymbol": "AAL260702P00010000",
            "lastTradeDate": "2026-06-11 16:36:08+00:00",
            "strike": 10.0,
            "lastPrice": 0.04,
            "bid": 0.0,
            "ask": 0.04,
            "change": 0.0,
            "percentChange": 0.0,
            "volume": 2.0,
            "openInterest": 100,
            "impliedVolatility": 0.87500125,
            "inTheMoney": false,
            "contractSize": "REGULAR",
            "currency": "USD"
        },
        {
            "contractSymbol": "AAL260702P00010500",
            "lastTradeDate": "2026-06-11 13:40:09+00:00",
            "strike": 10.5,
            "lastPrice": 0.09,
            "bid": 0.0,
            "ask": 0.04,
            "change": 0.0,
            "percentChange": 0.0,
            "volume": 1.0,
            "openInterest": 157,
            "impliedVolatility": 0.7812521875,
            "inTheMoney": false,
            "contractSize": "REGULAR",
            "currency": "USD"
        },
        {
            "contractSymbol": "AAL260702P00011000",
            "lastTradeDate": "2026-06-12 19:23:29+00:00",
            "strike": 11.0,
            "lastPrice": 0.03,
            "bid": 0.0,
            "ask": 0.05,
            "change": -0.049999997,
            "percentChange": -62.5,
            "volume": 2.0,
            "openInterest": 75,
            "impliedVolatility": 0.7187528125,
            "inTheMoney": false,
            "contractSize": "REGULAR",
            "currency": "USD"
        },
        {
            "contractSymbol": "AAL260702P00011500",
            "lastTradeDate": "2026-06-11 18:23:03+00:00",
            "strike": 11.5,
            "lastPrice": 0.05,
            "bid": 0.0,
            "ask": 2.16,
            "change": 0.0,
            "percentChange": 0.0,
            "volume": 63.0,
            "openInterest": 480,
            "impliedVolatility": 2.050786123046875,
            "inTheMoney": false,
            "contractSize": "REGULAR",
            "currency": "USD"
        },
        {
            "contractSymbol": "AAL260702P00012000",
            "lastTradeDate": "2026-06-12 19:33:14+00:00",
            "strike": 12.0,
            "lastPrice": 0.1,
            "bid": 0.05,
            "ask": 0.2,
            "change": 0.009999998,
            "percentChange": 11.111108,
            "volume": 257.0,
            "openInterest": 895,
            "impliedVolatility": 0.7851583984375,
            "inTheMoney": false,
            "contractSize": "REGULAR",
            "currency": "USD"
        },
        {
            "contractSymbol": "AAL260702P00012500",
            "lastTradeDate": "2026-06-12 19:06:06+00:00",
            "strike": 12.5,
            "lastPrice": 0.09,
            "bid": 0.07,
            "ask": 0.1,
            "change": -0.060000002,
            "percentChange": -40.0,
            "volume": 235.0,
            "openInterest": 849,
            "impliedVolatility": 0.6054726953125001,
            "inTheMoney": false,
            "contractSize": "REGULAR",
            "currency": "USD"
        },
        {
            "contractSymbol": "AAL260702P00013000",
            "lastTradeDate": "2026-06-12 19:27:30+00:00",
            "strike": 13.0,
            "lastPrice": 0.12,
            "bid": 0.1,
            "ask": 0.15,
            "change": -0.089999996,
            "percentChange": -42.857143,
            "volume": 66.0,
            "openInterest": 531,
            "impliedVolatility": 0.5664105859375,
            "inTheMoney": false,
            "contractSize": "REGULAR",
            "currency": "USD"
        },
        {
            "contractSymbol": "AAL260702P00013500",
            "lastTradeDate": "2026-06-12 19:46:06+00:00",
            "strike": 13.5,
            "lastPrice": 0.21,
            "bid": 0.18,
            "ask": 0.21,
            "change": -0.08,
            "percentChange": -27.586206,
            "volume": 97.0,
            "openInterest": 886,
            "impliedVolatility": 0.5410202148437502,
            "inTheMoney": false,
            "contractSize": "REGULAR",
            "currency": "USD"
        },
        {
            "contractSymbol": "AAL260702P00014000",
            "lastTradeDate": "2026-06-12 18:56:58+00:00",
            "strike": 14.0,
            "lastPrice": 0.31,
            "bid": 0.29,
            "ask": 0.32,
            "change": -0.15,
            "percentChange": -32.608696,
            "volume": 79.0,
            "openInterest": 405,
            "impliedVolatility": 0.5214891601562499,
            "inTheMoney": false,
            "contractSize": "REGULAR",
            "currency": "USD"
        },
        {
            "contractSymbol": "AAL260702P00014500",
            "lastTradeDate": "2026-06-12 17:26:58+00:00",
            "strike": 14.5,
            "lastPrice": 0.46,
            "bid": 0.44,
            "ask": 0.48,
            "change": -0.78999996,
            "percentChange": -63.199997,
            "volume": 67.0,
            "openInterest": 165,
            "impliedVolatility": 0.5019581054687501,
            "inTheMoney": false,
            "contractSize": "REGULAR",
            "currency": "USD"
        },
        {
            "contractSymbol": "AAL260702P00015000",
            "lastTradeDate": "2026-06-12 19:39:47+00:00",
            "strike": 15.0,
            "lastPrice": 0.71,
            "bid": 0.65,
            "ask": 0.7,
            "change": -0.54,
            "percentChange": -43.2,
            "volume": 119.0,
            "openInterest": 221,
            "impliedVolatility": 0.50586431640625,
            "inTheMoney": true,
            "contractSize": "REGULAR",
            "currency": "USD"
        },
        {
            "contractSymbol": "AAL260702P00015500",
            "lastTradeDate": "2026-06-12 19:42:49+00:00",
            "strike": 15.5,
            "lastPrice": 0.99,
            "bid": 0.93,
            "ask": 1.02,
            "change": -0.79999995,
            "percentChange": -44.692738,
            "volume": 522.0,
            "openInterest": 926,
            "impliedVolatility": 0.5273484765625001,
            "inTheMoney": true,
            "contractSize": "REGULAR",
            "currency": "USD"
        },
        {
            "contractSymbol": "AAL260702P00016000",
            "lastTradeDate": "2026-06-11 14:17:24+00:00",
            "strike": 16.0,
            "lastPrice": 2.5,
            "bid": 1.11,
            "ask": 1.64,
            "change": 0.0,
            "percentChange": 0.0,
            "volume": 1.0,
            "openInterest": 8,
            "impliedVolatility": 0.5390671093750001,
            "inTheMoney": true,
            "contractSize": "REGULAR",
            "currency": "USD"
        },
        {
            "contractSymbol": "AAL260702P00016500",
            "lastTradeDate": "2026-06-09 19:36:20+00:00",
            "strike": 16.5,
            "lastPrice": 1.85,
            "bid": 1.5,
            "ask": 2.22,
            "change": -0.51999986,
            "percentChange": -21.940924,
            "volume": 30.0,
            "openInterest": 36,
            "impliedVolatility": 0.632816171875,
            "inTheMoney": true,
            "contractSize": "REGULAR",
            "currency": "USD"
        },
        {
            "contractSymbol": "AAL260702P00017000",
            "lastTradeDate": "2026-06-11 13:33:50+00:00",
            "strike": 17.0,
            "lastPrice": 3.55,
            "bid": 1.91,
            "ask": 2.87,
            "change": 0.0,
            "percentChange": 0.0,
            "volume": 4.0,
            "openInterest": 4,
            "impliedVolatility": 0.75586181640625,
            "inTheMoney": true,
            "contractSize": "REGULAR",
            "currency": "USD"
        },
        {
            "contractSymbol": "AAL260702P00017500",
            "lastTradeDate": "2026-06-11 14:01:18+00:00",
            "strike": 17.5,
            "lastPrice": 3.8,
            "bid": 1.35,
            "ask": 3.85,
            "change": 0.0,
            "percentChange": 0.0,
            "volume": 2.0,
            "openInterest": 6,
            "impliedVolatility": 0.5117236328125,
            "inTheMoney": true,
            "contractSize": "REGULAR",
            "currency": "USD"
        },
        {
            "contractSymbol": "AAL260702P00018000",
            "lastTradeDate": "2026-06-08 15:22:13+00:00",
            "strike": 18.0,
            "lastPrice": 3.15,
            "bid": 2.13,
            "ask": 4.3,
            "change": -1.19,
            "percentChange": -27.419355,
            "volume": 35.0,
            "openInterest": 14,
            "impliedVolatility": 0.7402369726562499,
            "inTheMoney": true,
            "contractSize": "REGULAR",
            "currency": "USD"
        },
        {
            "contractSymbol": "AAL260702P00019000",
            "lastTradeDate": "2026-06-11 13:32:55+00:00",
            "strike": 19.0,
            "lastPrice": 5.6,
            "bid": 3.75,
            "ask": 4.95,
            "change": 0.0,
            "percentChange": 0.0,
            "volume": 4.0,
            "openInterest": 7,
            "impliedVolatility": 1.0390673046875003,
            "inTheMoney": true,
            "contractSize": "REGULAR",
            "currency": "USD"
        },
        {
            "contractSymbol": "AAL260702P00020000",
            "lastTradeDate": "2026-06-10 13:52:56+00:00",
            "strike": 20.0,
            "lastPrice": 6.23,
            "bid": 4.75,
            "ask": 5.75,
            "change": 0.0,
            "percentChange": 0.0,
            "volume": 2.0,
            "openInterest": 7,
            "impliedVolatility": 1.052739111328125,
            "inTheMoney": true,
            "contractSize": "REGULAR",
            "currency": "USD"
        },
        {
            "contractSymbol": "AAL260702P00021000",
            "lastTradeDate": "2026-06-12 19:16:49+00:00",
            "strike": 21.0,
            "lastPrice": 5.97,
            "bid": 5.65,
            "ask": 6.55,
            "change": -1.3300004,
            "percentChange": -18.219183,
            "volume": 5.0,
            "openInterest": 0,
            "impliedVolatility": 0.9101571484375,
            "inTheMoney": true,
            "contractSize": "REGULAR",
            "currency": "USD"
        },
        {
            "contractSymbol": "AAL260702P00022000",
            "lastTradeDate": "2026-06-12 13:35:00+00:00",
            "strike": 22.0,
            "lastPrice": 7.19,
            "bid": 6.7,
            "ask": 7.35,
            "change": -1.4199996,
            "percentChange": -16.492447,
            "volume": 6.0,
            "openInterest": 3,
            "impliedVolatility": 0.6562534375000001,
            "inTheMoney": true,
            "contractSize": "REGULAR",
            "currency": "USD"
        }
    ]
}